ymj_tool/__init__.py
ymj_tool/_dummy.cp39-win32.pyd
ymj_tool/common_utils.py
ymj_tool/pyarmor_runtime_000000/__init__.py
ymj_tool/pyarmor_runtime_000000/pyarmor_runtime.pyd
ymj_tool-1.0.12.dist-info/METADATA
ymj_tool-1.0.12.dist-info/WHEEL
ymj_tool-1.0.12.dist-info/top_level.txt
ymj_tool-1.0.12.dist-info/RECORD
