Metadata-Version: 2.2
Name: ymj_tool
Version: 1.0.12
Summary: A useful tool for ...
Author: ssseVennn
Author-email: 739369987@qq.com
Classifier: Programming Language :: Python :: 3
Classifier: Operating System :: OS Independent
Requires-Python: >=3.9
Dynamic: author
Dynamic: author-email
Dynamic: classifier
Dynamic: requires-python
Dynamic: summary
